pptxvars/__init__.py
pptxvars/cli.py
pptxvars/image_swap.py
pptxvars/pipeline.py
pptxvars/replacer.py
pptxvars-1.0.1.dist-info/licenses/LICENSE
pptxvars-1.0.1.dist-info/METADATA
pptxvars-1.0.1.dist-info/WHEEL
pptxvars-1.0.1.dist-info/entry_points.txt
pptxvars-1.0.1.dist-info/top_level.txt
pptxvars-1.0.1.dist-info/RECORD
