Metadata-Version: 2.4
Name: pptxvars
Version: 1.0.1
Summary: Replace {{KEY}} tokens in PPTX while preserving styling & swap frame shapes for images in while preserving sizes
Project-URL: Homepage, https://github.com/luukdick/pptxvars
Requires-Python: >=3.12
License-File: LICENSE
Requires-Dist: python-pptx>=1.0.2
Requires-Dist: pyyaml>=6.0.2
Dynamic: license-file
